danmu/__init__.py
danmu/danmu.py
danmu/pack.py
bili_danmu-0.2.5.dist-info/WHEEL
bili_danmu-0.2.5.dist-info/METADATA
bili_danmu-0.2.5.dist-info/RECORD
