Metadata-Version: 2.1
Name: bili-danmu
Version: 0.2.5
Summary: A modern library for receiving danmu from bilibili livestream
License: MIT
Author: WorldObservationLog
Author-email: wolc@duck.com
Requires-Python: >=3.10,<4.0
Classifier: License :: OSI Approved :: MIT License
Classifier: Programming Language :: Python :: 3
Classifier: Programming Language :: Python :: 3.10
Classifier: Programming Language :: Python :: 3.11
Requires-Dist: brotlipy (>=0.7.0,<0.8.0)
Requires-Dist: websockets (>=10.4,<11.0)
Project-URL: GitHub, https://github.com/WorldObservationLog/bili-danmu
